project_Screenshot/__init__.py
project_Screenshot/r_screenshot.py
project_Screenshot/shutter.mp3
project_Screenshot/utilities.py
rk_screenshot-1.3.1.dist-info/LICENSE
rk_screenshot-1.3.1.dist-info/METADATA
rk_screenshot-1.3.1.dist-info/WHEEL
rk_screenshot-1.3.1.dist-info/top_level.txt
rk_screenshot-1.3.1.dist-info/RECORD
