Metadata-Version: 2.1
Name: rk_screenshot
Version: 1.3.1
Summary: Screenshot using Gesture hand detection
Author: Rohit Kumar Yadav
Author-email: <rohitkuyadav2003@gmail.com>
License: MIT
Keywords: python,video,stream,video stream,camera stream,sockets
Classifier: Development Status :: 1 - Planning
Classifier: Intended Audience :: Developers
Classifier: Programming Language :: Python :: 3
Classifier: Operating System :: Unix
Classifier: Operating System :: MacOS :: MacOS X
Classifier: Operating System :: Microsoft :: Windows
Classifier: Operating System :: POSIX :: Linux
License-File: LICENSE
Requires-Dist: pyscreenshot
Requires-Dist: opencv-python
Requires-Dist: mediapipe
Requires-Dist: playsound
